laspy/__init__.py
laspy/_pointappender.py
laspy/_pointreader.py
laspy/_pointwriter.py
laspy/compression.py
laspy/copc.py
laspy/errors.py
laspy/extradims.py
laspy/file.py
laspy/header.py
laspy/lasappender.py
laspy/lasdata.py
laspy/lasmmap.py
laspy/lasreader.py
laspy/laswriter.py
laspy/lib.py
laspy/lib.pyi
laspy/typehints.py
laspy/utils.py
laspy/_compression/__init__.py
laspy/_compression/backend.py
laspy/_compression/format.py
laspy/_compression/laszipbackend.py
laspy/_compression/lazbackend.py
laspy/_compression/lazrsbackend.py
laspy/_compression/selection.py
laspy/cli/__init__.py
laspy/cli/copc.py
laspy/cli/core.py
laspy/cli/main.py
laspy/point/__init__.py
laspy/point/dims.py
laspy/point/format.py
laspy/point/packing.py
laspy/point/record.py
laspy/vlrs/__init__.py
laspy/vlrs/geotiff.py
laspy/vlrs/known.py
laspy/vlrs/vlr.py
laspy/vlrs/vlrlist.py
laspy-2.6.0.dist-info/licenses/LICENSE.txt
laspy-2.6.0.dist-info/METADATA
laspy-2.6.0.dist-info/WHEEL
laspy-2.6.0.dist-info/entry_points.txt
laspy-2.6.0.dist-info/top_level.txt
laspy-2.6.0.dist-info/RECORD
